{"/_app":"pages/_app.js","/about":"pages/about.html","/admin":"pages/admin.html","/auth/signup":"pages/auth/signup.html","/auth/login":"pages/auth/login.html","/cart":"pages/cart.html","/dashboard/admin":"pages/dashboard/admin.html","/dashboard/customer":"pages/dashboard/customer.html","/dashboard/seller":"pages/dashboard/seller.html","/kids":"pages/kids.html","/":"pages/index.html","/men":"pages/men.html","/product/[id]":"pages/product/[id].html","/products":"pages/products.html","/checkout":"pages/checkout.html","/rider":"pages/rider.html","/urbannext":"pages/urbannext.html","/women":"pages/women.html","/messages":"pages/messages.html","/products/[slug]":"pages/products/[slug].html","/_document":"pages/_document.js","/_error":"pages/_error.js","/404":"pages/404.html"}